play_launch/__init__.py
play_launch/cli.py
play_launch/io_helper_cli.py
play_launch/analyzer/__init__.py
play_launch/analyzer/plot_resource_usage.py
play_launch/bin/play_launch
play_launch/bin/play_launch_io_helper
play_launch/dump/__init__.py
play_launch/dump/__main__.py
play_launch/dump/event_handlers.py
play_launch/dump/inspector.py
play_launch/dump/launch_dump.py
play_launch/dump/ros_cmdline.py
play_launch/dump/utils.py
play_launch/dump/visitor/__init__.py
play_launch/dump/visitor/action.py
play_launch/dump/visitor/composable_node_container.py
play_launch/dump/visitor/entity.py
play_launch/dump/visitor/execute_local.py
play_launch/dump/visitor/execute_process.py
play_launch/dump/visitor/include_launch_description.py
play_launch/dump/visitor/lifecycle_node.py
play_launch/dump/visitor/load_composable_nodes.py
play_launch/dump/visitor/node.py
play_launch-0.5.1.dist-info/licenses/LICENSE.txt
play_launch-0.5.1.dist-info/METADATA
play_launch-0.5.1.dist-info/WHEEL
play_launch-0.5.1.dist-info/entry_points.txt
play_launch-0.5.1.dist-info/top_level.txt
play_launch-0.5.1.dist-info/RECORD
