Metadata-Version: 2.4
Name: play_launch
Version: 0.5.1
Summary: ROS2 Launch Inspection Tool - Record and replay launch executions for performance analysis
Author-email: "Lin, Hsiang-Jui" <jerry73204@gmail.com>
License-Expression: BSD-3-Clause
Project-URL: Repository, https://github.com/NEWSLabNTU/play_launch
Project-URL: Documentation, https://github.com/NEWSLabNTU/play_launch#readme
Keywords: ros2,launch,profiling,monitoring,robotics
Classifier: Development Status :: 4 - Beta
Classifier: Environment :: Console
Classifier: Intended Audience :: Developers
Classifier: Operating System :: POSIX :: Linux
Classifier: Programming Language :: Python :: 3
Classifier: Programming Language :: Python :: 3.10
Classifier: Programming Language :: Python :: 3.11
Classifier: Programming Language :: Python :: 3.12
Classifier: Programming Language :: Rust
Classifier: Topic :: Software Development :: Testing
Classifier: Topic :: System :: Monitoring
Requires-Python: >=3.10
License-File: LICENSE.txt
Requires-Dist: pyyaml>=6.0
Requires-Dist: lark>=1.2
Requires-Dist: packaging>=24.0
Requires-Dist: plotly>=5.4.1
Provides-Extra: dev
Requires-Dist: pytest>=8.0; extra == "dev"
Requires-Dist: pytest-cov>=4.1; extra == "dev"
Requires-Dist: pytest-mock>=3.12; extra == "dev"
Requires-Dist: ruff>=0.8.0; extra == "dev"
Requires-Dist: build; extra == "dev"
Dynamic: license-file
